{
  "collapse-filter": true,
  "search": "-path:templates ",
  "showTags": false,
  "showAttachments": false,
  "hideUnresolved": false,
  "showOrphans": true,
  "collapse-color-groups": false,
  "colorGroups": [
    {
      "query": "tag:#indexzettel  ",
      "color": {
        "a": 1,
        "rgb": 15861511
      }
    },
    {
      "query": "tag:#projektzettel  ",
      "color": {
        "a": 1,
        "rgb": 16514816
      }
    },
    {
      "query": "tag:#themenzettel  ",
      "color": {
        "a": 1,
        "rgb": 4972855
      }
    },
    {
      "query": "tag:#notizzettel  ",
      "color": {
        "a": 1,
        "rgb": 13311
      }
    },
    {
      "query": "tag:#void  ",
      "color": {
        "a": 1,
        "rgb": 5431473
      }
    },
    {
      "query": "tag:#literaturzettel  ",
      "color": {
        "a": 1,
        "rgb": 16777215
      }
    }
  ],
  "collapse-display": true,
  "showArrow": true,
  "textFadeMultiplier": 0,
  "nodeSizeMultiplier": 1,
  "lineSizeMultiplier": 1,
  "collapse-forces": true,
  "centerStrength": 0.518713248970312,
  "repelStrength": 10,
  "linkStrength": 1,
  "linkDistance": 250,
  "scale": 1.0000000000000004,
  "close": true
}